my_tail/__init__.py
my_tail/main.py
my_tail_yura_maksym-0.1.0.dist-info/licenses/LICENSE
my_tail_yura_maksym-0.1.0.dist-info/METADATA
my_tail_yura_maksym-0.1.0.dist-info/WHEEL
my_tail_yura_maksym-0.1.0.dist-info/entry_points.txt
my_tail_yura_maksym-0.1.0.dist-info/top_level.txt
my_tail_yura_maksym-0.1.0.dist-info/RECORD
